serenest/__init__.py
serenest/cryptoutils.py
serenest/data_wrangling.py
serenest/dlputils.py
serenest-0.3.0.dist-info/METADATA
serenest-0.3.0.dist-info/WHEEL
serenest-0.3.0.dist-info/top_level.txt
serenest-0.3.0.dist-info/RECORD
