Metadata-Version: 2.1
Name: serenest
Version: 0.3.0
Summary: cryptography tools for CTF, by Serenest
Home-page: https://gitlab.com/Serenest/serenest
Author: Serenest
Author-email: serenest.ctf@gmail.com
License: MIT
Platform: UNKNOWN
Classifier: License :: OSI Approved :: MIT License
Classifier: Programming Language :: Python :: 3
